<panel>
	<attachment_group class="vertical_arrange_autosize" vertical_offset="0" horizontal_alignment="horizontal" horizontal_inset="0" />

	<boolean id="check_for_multiple_requests" value="true"/>

	<!-- some descriptive text for the table below -->
	<widget class="text" id="titl" auto_size="vertical" spec="text" colour="text" font="fonts/inbox_body" size="11"/>

	<!-- view props specific to this panel -->
	<boolean id="database_table_type" value="1"/>
	<list id="viewed_property_ids">
		<integer value="Pnms"/>
		<integer value="Ppos"/>
		<integer value="Pclb"/>
		<integer value="Pcab"/>
		<integer value="Ppab"/>
		<integer value="Poap"/>
		<integer value="Pogl"/>
		<integer value="Poas"/>
		<integer value="Poav"/>
	</list>

	<widget class="table" id="list" mode="fill_rows, stripe_rows, printable, keyboard, show_bullets, select_rows, select_multiple, dont_ask_for_focus" fixed_size_rows="true" auto_size="vertical">
		<string id="customise_view_panel_class" value="customise_view_advanced_panel"/>
	</widget>

</panel>