<panel>

	<attachment_group class="vertical_arrange_autosize" vertical_alignment="top" vertical_gap="6"/>
	<container class="main_box" id="head" height="70" file="tutorial/widgets/induction experienced panel header" />

	<!-- We will be adding the core parts of the panel in code -->
	<container id="cont">
		<attachment_group class="vertical_arrange_autosize" />
	</container>

	<!-- Buttons -->
	<container>
		<attachment_group class="horizontal_arrange_vertical_autosize" horizontal_alignment="left,extend" >
			<global id="horizontal_gap" name="ui.button_row_gap"/>
      	</attachment_group>
      	
		<!-- Skip Button -->
		<widget class="icon_button" id="skip" height="30" auto_size="horizontal" primay_icon_enabled="false" gamepad_icon_aligment="centre_right" font="title" click_event="SkTo" alignment="centre">
			<translation id="text" translation_id="332276" type="use" value="Skip[COMMENT: match_time_slider; instruction to skip the replay]" />
			<string id="controller_button" value="1" />
		</widget>
		<!-- Start Button Button -->
		<widget class="primary_icon_button" id="STRb" height="30" font="title" click_event="STut" alignment="centre" red_replacement="white" colour="fm purple" icon_colour="fm purple" secondary_icon_colour="fm purple" controller_button="y_button" />
	</container>
	<container class="main_contrast_box" appearance="boxes/custom/solid/rounded/paper"  id="resC" red_replacement="deep purple 500" hidden="true">
		<attachment_group class="vertical_arrange_autosize" horizontal_inset="8" vertical_offset="8" vertical_gap="8"/>
		<widget class="text" font="title" auto_size="vertical" colour="text">
			<translation id="text" translation_id="335274" type="use" value="Responsibilities[COMMENT: Manager main/top menu: national team options when team name is not visible]" />
		</widget>
		<container id="resp">
			<layout class="fit_children_attachment" alignment="vertical,extend" offset="0" />
			<layout class="arrange_items_attachment" alignment="left" gap="15" offset="0"/>
			<!-- We will programatically add decisions here e.g scouting control: head coach or manager-->
		</container>
	</container>
</panel>